{"status": "OK", "copyright": "Copyright (c) 2017 The New York Times Company. All Rights Reserved.", "has_more": true, "num_results": 20, "results": [{"display_title": "The Amorous Adventures of Moll Flanders", "mpaa_rating": "", "critics_pick": 0, "byline": "HOWARD THOMPSON.", "headline": "Amorous Adventures of Moll Flanders, The (Movie)", "summary_short": "Ornate, gamely acted, but overstretched. Palmer steals it.", "publication_date": "1965-05-27", "opening_date": null, "date_updated": "2016-03-30 07:18:02", "link": {"type": "article", "url": "http://www.nytimes.com/movie/review?res=9C03E3DC163BE13ABC4F51DFB366838E679EDE", "suggested_link_text": "Read the New York Times Review of The Amorous Adventures of Moll Flanders"}, "multimedia": null}, {"display_title": "China", "mpaa_rating": "", "critics_pick": 0, "byline": "A.H. WEILER", "headline": "China (Movie)", "summary_short": "", "publication_date": "1965-05-26", "opening_date": null, "date_updated": "2016-03-30 06:51:25", "link": {"type": "article", "url": "http://www.nytimes.com/movie/review?res=940DE0DF133CE733A25755C2A9639C946491D6CF", "suggested_link_text": "Read the New York Times Review of China"}, "multimedia": null}, {"display_title": "Murder Most Foul", "mpaa_rating": "Not Rated", "critics_pick": 0, "byline": "A.H. WEILER", "headline": "Murder Most Foul (Movie)", "summary_short": "Weakest Miss Marple-Christie whodunit for dauntless Maggie.", "publication_date": "1965-05-24", "opening_date": null, "date_updated": "2016-03-30 06:56:46", "link": {"type": "article", "url": "http://www.nytimes.com/movie/review?res=9405EED6123CE733A25757C2A9639C946491D6CF", "suggested_link_text": "Read the New York Times Review of Murder Most Foul"}, "multimedia": null}, {"display_title": "On the Fiddle", "mpaa_rating": "", "critics_pick": 0, "byline": "HOWARD THOMPSON", "headline": "Operation Snafu (Movie)", "summary_short": "Early Connery, and old Army romp about two pals, brain (Lynch) and brawn (Sean). Friendly, perky, easy to take.", "publication_date": "1965-05-22", "opening_date": "1965-01-27", "date_updated": "2016-03-30 06:51:26", "link": {"type": "article", "url": "http://www.nytimes.com/movie/review?res=9A07E0D8123CE733A25751C2A9639C946491D6CF", "suggested_link_text": "Read the New York Times Review of On the Fiddle"}, "multimedia": null}, {"display_title": "Signpost to Murder", "mpaa_rating": "", "critics_pick": 0, "byline": "HOWARD THOMPSON", "headline": "Signpost to Murder (Movie)", "summary_short": "Extremely talky suspense, via the stage. Real star is that house with interior mill-wheel.", "publication_date": "1965-05-20", "opening_date": null, "date_updated": "2016-03-30 07:23:02", "link": {"type": "article", "url": "http://www.nytimes.com/movie/review?res=9800EFDD1039EE32A25753C2A9639C946491D6CF", "suggested_link_text": "Read the New York Times Review of Signpost to Murder"}, "multimedia": null}, {"display_title": "Die! Die! My Darling!", "mpaa_rating": "Not Rated", "critics_pick": 0, "byline": "A.H. WEILER", "headline": "Die! Die! My Darling (Movie)", "summary_short": "Dies like a dog, with a howling Tallu.", "publication_date": "1965-05-20", "opening_date": null, "date_updated": "2016-03-30 07:05:40", "link": {"type": "article", "url": "http://www.nytimes.com/movie/review?res=9D00EFDD1039EE32A25753C2A9639C946491D6CF", "suggested_link_text": "Read the New York Times Review of Die! Die! My Darling!"}, "multimedia": null}, {"display_title": "Harlow", "mpaa_rating": "", "critics_pick": 0, "byline": "HOWARD THOMPSON", "headline": "Harlow (Movie)", "summary_short": "Story of blond bombshell Jean. Trash, but evocative early-Hollywood ambiance.", "publication_date": "1965-05-15", "opening_date": "1965-06-23", "date_updated": "2016-03-30 07:15:48", "link": {"type": "article", "url": "http://www.nytimes.com/movie/review?res=9F02E6DE163BE13ABC4D52DFB366838E679EDE", "suggested_link_text": "Read the New York Times Review of Harlow"}, "multimedia": null}, {"display_title": "The Yellow Rolls-Royce", "mpaa_rating": "", "critics_pick": 0, "byline": "A.H. WEILER", "headline": "Yellow Rolls-Royce, The (Movie)", "summary_short": "Three yarns, same car: Ascot flat, lukewarm pizza, wartime waffle. Stars do not a gas tank fill.", "publication_date": "1965-05-14", "opening_date": "1965-05-13", "date_updated": "2016-03-30 07:23:34", "link": {"type": "article", "url": "http://www.nytimes.com/movie/review?res=9F0DE0D9123CE733A25757C1A9639C946491D6CF", "suggested_link_text": "Read the New York Times Review of The Yellow Rolls-Royce"}, "multimedia": null}, {"display_title": "Young Dillinger", "mpaa_rating": "", "critics_pick": 0, "byline": "EUGENE ARCHER.", "headline": "Young Dillinger (Movie)", "summary_short": "The 30's outlaw teams up with Pretty Boy Floyd, Baby Face Nelson and Homer Van Meter.", "publication_date": "1965-05-13", "opening_date": "1965-04-28", "date_updated": "2016-03-30 07:28:57", "link": {"type": "article", "url": "http://www.nytimes.com/movie/review?res=950DE0DF163BE13ABC4B52DFB366838E679EDE", "suggested_link_text": "Read the New York Times Review of Young Dillinger"}, "multimedia": null}, {"display_title": "Mister Moses", "mpaa_rating": "", "critics_pick": 0, "byline": "A.H. WEILER", "headline": "Mister Moses (Movie)", "summary_short": "Lost in the bulrushes. Good African locale.", "publication_date": "1965-05-13", "opening_date": null, "date_updated": "2016-03-30 06:47:16", "link": {"type": "article", "url": "http://www.nytimes.com/movie/review?res=990DE0DF163BE13ABC4B52DFB366838E679EDE", "suggested_link_text": "Read the New York Times Review of Mister Moses"}, "multimedia": null}, {"display_title": "Sammy Going South", "mpaa_rating": "", "critics_pick": 0, "byline": "HOWARD THOMPSON.", "headline": "Boy Ten Feet Tall, A (Movie)", "summary_short": "War orphan treks length of Africa. Bit above-average, scenery more so.", "publication_date": "1965-05-13", "opening_date": null, "date_updated": "2016-03-30 06:42:48", "link": {"type": "article", "url": "http://www.nytimes.com/movie/review?res=940DE0DF163BE13ABC4B52DFB366838E679EDE", "suggested_link_text": "Read the New York Times Review of Sammy Going South"}, "multimedia": null}, {"display_title": "Hollywood My Hometown", "mpaa_rating": "", "critics_pick": 0, "byline": "HOWARD THOMPSON", "headline": "Hollywood My Hometown (Movie)", "summary_short": "", "publication_date": "1965-05-11", "opening_date": null, "date_updated": "2016-03-30 07:23:22", "link": {"type": "article", "url": "http://www.nytimes.com/movie/review?res=9D07E4DF163BE13ABC4952DFB366838E679EDE", "suggested_link_text": "Read the New York Times Review of Hollywood My Hometown"}, "multimedia": null}, {"display_title": "Goldstein", "mpaa_rating": "", "critics_pick": 0, "byline": "EUGENE ARCHER", "headline": "Goldstein (Movie)", "summary_short": "", "publication_date": "1965-05-08", "opening_date": null, "date_updated": "2016-03-30 06:42:14", "link": {"type": "article", "url": "http://www.nytimes.com/movie/review?res=9407E1DA123CE733A2575BC0A9639C946491D6CF", "suggested_link_text": "Read the New York Times Review of Goldstein"}, "multimedia": null}, {"display_title": "Variety Lights", "mpaa_rating": "Not Rated", "critics_pick": 0, "byline": "A.H. WEILER", "headline": "Luci del Varieta (Movie)", "summary_short": "Italian star born from ragtag music-hall troupe. Touching, picaresque vignettes. Fellini co-directed.", "publication_date": "1965-05-07", "opening_date": null, "date_updated": "2016-03-30 06:42:18", "link": {"type": "article", "url": "http://www.nytimes.com/movie/review?res=9400EED81F38E13ABC4F53DFB366838E679EDE", "suggested_link_text": "Read the New York Times Review of Variety Lights"}, "multimedia": null}, {"display_title": "The Tomb of Ligeia", "mpaa_rating": "Not Rated", "critics_pick": 0, "byline": "HOWARD THOMPSON.", "headline": "Tomb of Ligeia (Movie)", "summary_short": "Artful, imaginative Poe derivation, via Roger Corman. Quite surprising.", "publication_date": "1965-05-06", "opening_date": "1965-01-20", "date_updated": "2016-03-30 06:42:28", "link": {"type": "article", "url": "http://www.nytimes.com/movie/review?res=9B00E5DA123CE733A25755C0A9639C946491D6CF", "suggested_link_text": "Read the New York Times Review of The Tomb of Ligeia"}, "multimedia": null}, {"display_title": "Synanon", "mpaa_rating": "", "critics_pick": 0, "byline": "A.H. WEILER", "headline": "Synanon (Movie)", "summary_short": "The drug-addict rehabilitation center. On the whole, very admirable drama for its time.", "publication_date": "1965-05-06", "opening_date": null, "date_updated": "2016-03-30 06:53:13", "link": {"type": "article", "url": "http://www.nytimes.com/movie/review?res=9A00E5DA123CE733A25755C0A9639C946491D6CF", "suggested_link_text": "Read the New York Times Review of Synanon"}, "multimedia": null}, {"display_title": "I Nuovi Angeli", "mpaa_rating": "", "critics_pick": 0, "byline": "A.H. WEILER", "headline": "New Angels, The (Movie)", "summary_short": "", "publication_date": "1965-05-04", "opening_date": null, "date_updated": "2016-03-30 07:12:01", "link": {"type": "article", "url": "http://www.nytimes.com/movie/review?res=9806E6DB123CE733A25757C0A9639C946491D6CF", "suggested_link_text": "Read the New York Times Review of I Nuovi Angeli"}, "multimedia": null}, {"display_title": "Get Yourself a College Girl", "mpaa_rating": "", "critics_pick": 0, "byline": "HOWARD THOMPSON.", "headline": "Get Yourself a College Girl (Movie)", "summary_short": "And two aspirins.", "publication_date": "1965-04-29", "opening_date": "1964-12-18", "date_updated": "2016-03-30 07:15:11", "link": {"type": "article", "url": "http://www.nytimes.com/movie/review?res=9501E4DE1F30E033A2575AC2A9629C946491D6CF", "suggested_link_text": "Read the New York Times Review of Get Yourself a College Girl"}, "multimedia": null}, {"display_title": "Masquerade", "mpaa_rating": "", "critics_pick": 0, "byline": "EUGENE ARCHER.", "headline": "Masquerade (Movie)", "summary_short": "Neat, twisty Middle East intrigue. Deft young Cliff.", "publication_date": "1965-04-29", "opening_date": null, "date_updated": "2016-03-30 06:49:04", "link": {"type": "article", "url": "http://www.nytimes.com/movie/review?res=9E00E4DE1F30E033A2575AC2A9629C946491D6CF", "suggested_link_text": "Read the New York Times Review of Masquerade"}, "multimedia": null}, {"display_title": "Il Successo", "mpaa_rating": "", "critics_pick": 0, "byline": "BOSLEY CROWTHER", "headline": "Successo, Il (Movie)", "summary_short": "", "publication_date": "1965-04-29", "opening_date": null, "date_updated": "2016-03-30 07:05:56", "link": {"type": "article", "url": "http://www.nytimes.com/movie/review?res=9401E4DE1F30E033A2575AC2A9629C946491D6CF", "suggested_link_text": "Read the New York Times Review of Il Successo"}, "multimedia": null}]}