{"results": [{"display_title": "Bandolero", "date_updated": "2016-03-30 06:58:06", "byline": "MORDAUNT HALL.", "mpaa_rating": "", "headline": "Bandolero, The", "summary_short": "", "publication_date": "1924-10-27", "link": {"type": "article", "suggested_link_text": "Read the New York Times Review of Bandolero", "url": "http://www.nytimes.com/movie/review?res=9C00E7D8103BE233A25754C2A9669D946595D6CF"}, "opening_date": "1924-10-20", "critics_pick": 0, "multimedia": null}, {"display_title": "Silent Watcher", "date_updated": "2016-03-30 07:27:22", "byline": "MORDAUNT HALL.", "mpaa_rating": "", "headline": "Silent Watcher, The", "summary_short": "", "publication_date": "1924-10-26", "link": {"type": "article", "suggested_link_text": "Read the New York Times Review of Silent Watcher", "url": "http://www.nytimes.com/movie/review?res=9E00EFDE1038E233A25755C2A9669D946595D6CF"}, "opening_date": "1924-10-05", "critics_pick": 0, "multimedia": null}, {"display_title": "Speed Spook", "date_updated": "2016-03-30 07:16:08", "byline": "MORDAUNT HALL.", "mpaa_rating": "", "headline": "Speed Spook, The", "summary_short": "", "publication_date": "1924-10-21", "link": {"type": "article", "suggested_link_text": "Read the New York Times Review of Speed Spook", "url": "http://www.nytimes.com/movie/review?res=9A00EEDA103BE233A25752C2A9669D946595D6CF"}, "opening_date": "1924-08-30", "critics_pick": 0, "multimedia": null}, {"display_title": "Roaring Rails", "date_updated": "2016-03-30 07:15:31", "byline": "MORDAUNT HALL.", "mpaa_rating": "", "headline": "Roaring Rails", "summary_short": "", "publication_date": "1924-10-15", "link": {"type": "article", "suggested_link_text": "Read the New York Times Review of Roaring Rails", "url": "http://www.nytimes.com/movie/review?res=9F05E0DC1339E233A25756C1A9669D946595D6CF"}, "opening_date": "1924-09-21", "critics_pick": 0, "multimedia": null}, {"display_title": "Dangerous Money", "date_updated": "2016-03-30 07:13:24", "byline": "MORDAUNT HALL.", "mpaa_rating": "", "headline": "Dangerous Money", "summary_short": "", "publication_date": "1924-10-14", "link": {"type": "article", "suggested_link_text": "Read the New York Times Review of Dangerous Money", "url": "http://www.nytimes.com/movie/review?res=9903E1D8173FE733A25757C1A9669D946595D6CF"}, "opening_date": "1924-10-13", "critics_pick": 0, "multimedia": null}, {"display_title": "The Navigator", "date_updated": "2016-03-30 07:27:33", "byline": "MORDAUNT HALL.", "mpaa_rating": "Not Rated", "headline": "Navigator, The", "summary_short": "Silent. Millionaire and girlfriend drifting alone at sea.", "publication_date": "1924-10-13", "link": {"type": "article", "suggested_link_text": "Read the New York Times Review of The Navigator", "url": "http://www.nytimes.com/movie/review?res=9B0DE4DC1339E233A25750C1A9669D946595D6CF"}, "opening_date": "1924-10-13", "critics_pick": 0, "multimedia": null}, {"display_title": "Vanity's Price", "date_updated": "2016-03-30 06:51:51", "byline": "MORDAUNT HALL.", "mpaa_rating": "", "headline": "Vanity's Price", "summary_short": "", "publication_date": "1924-10-08", "link": {"type": "article", "suggested_link_text": "Read the New York Times Review of Vanity's Price", "url": "http://www.nytimes.com/movie/review?res=9906E0DB1239EF32A2575BC0A9669D946595D6CF"}, "opening_date": "1924-09-07", "critics_pick": 0, "multimedia": null}, {"display_title": "Her Love Story", "date_updated": "2016-03-30 06:55:33", "byline": "MORDAUNT HALL.", "mpaa_rating": "", "headline": "Her Love Story", "summary_short": "", "publication_date": "1924-10-07", "link": {"type": "article", "suggested_link_text": "Read the New York Times Review of Her Love Story", "url": "http://www.nytimes.com/movie/review?res=9B01EFDB103BE233A25754C0A9669D946595D6CF"}, "opening_date": "1924-10-06", "critics_pick": 0, "multimedia": null}, {"display_title": "Story without a Name", "date_updated": "2016-03-30 07:26:49", "byline": "MORDAUNT HALL.", "mpaa_rating": "", "headline": "Story Without a Name, The", "summary_short": "", "publication_date": "1924-10-06", "link": {"type": "article", "suggested_link_text": "Read the New York Times Review of Story without a Name", "url": "http://www.nytimes.com/movie/review?res=9807E6DC1339E233A25755C0A9669D946595D6CF"}, "opening_date": "1924-10-27", "critics_pick": 0, "multimedia": null}, {"display_title": "Divorce", "date_updated": "2016-03-30 07:26:24", "byline": "Special to The New York Times.", "mpaa_rating": "", "headline": "Divorce", "summary_short": "", "publication_date": "1923-06-26", "link": {"type": "article", "suggested_link_text": "Read the New York Times Review of Divorce", "url": "http://www.nytimes.com/movie/review?res=990CE5DF1430E333A25755C2A9609C946295D6CF"}, "opening_date": "1923-06-10", "critics_pick": 0, "multimedia": null}, {"display_title": "Hard Luck", "date_updated": "2016-03-30 06:45:21", "byline": "Special to The New York Times.", "mpaa_rating": "", "headline": "Hard Luck", "summary_short": "", "publication_date": "1921-06-20", "link": {"type": "article", "suggested_link_text": "Read the New York Times Review of Hard Luck", "url": "http://www.nytimes.com/movie/review?res=9802E2D9163EEE3ABC4851DFB066838A639EDE"}, "opening_date": "1921-03-14", "critics_pick": 0, "multimedia": null}, {"display_title": "The Real Thing at Last", "date_updated": "2016-03-30 07:26:09", "byline": "Special Cable to THE NEW YORK TIMES.", "mpaa_rating": "", "headline": "Real Thing at Last, The", "summary_short": "", "publication_date": "1916-03-09", "link": {"type": "article", "suggested_link_text": "Read the New York Times Review of The Real Thing at Last", "url": "http://www.nytimes.com/movie/review?res=9E03E7D7103FE233A2575AC0A9659C946796D6CF"}, "opening_date": "1916-04-22", "critics_pick": 0, "multimedia": null}, {"display_title": "How Molly Made Good", "date_updated": "2016-03-30 06:50:24", "byline": "Special to The New York Times.", "mpaa_rating": "", "headline": "How Molly Made Good", "summary_short": "", "publication_date": "1915-10-20", "link": {"type": "article", "suggested_link_text": "Read the New York Times Review of How Molly Made Good", "url": "http://www.nytimes.com/movie/review?res=9D07E2DC1239E333A25753C2A9669D946496D6CF"}, "opening_date": "1915-10-26", "critics_pick": 0, "multimedia": null}], "status": "OK", "num_results": 13, "copyright": "Copyright (c) 2017 The New York Times Company. All Rights Reserved.", "has_more": false}